kalx/__init__.py
kalx/__main__.py
kalx/api.py
kalx/auth/__init__.py
kalx/auth/authentication.py
kalx/auth/firebase_auth.py
kalx/auth/user.py
kalx/auth/validation.py
kalx/chat/__init__.py
kalx/chat/group.py
kalx/chat/message.py
kalx/chat/private.py
kalx/commands/__init__.py
kalx/commands/admin_commands.py
kalx/commands/command_descriptions.py
kalx/commands/command_handler.py
kalx/commands/group_commands.py
kalx/commands/message_commands.py
kalx/commands/system_commands.py
kalx/commands/user_commands.py
kalx/commands/user_commands_Backup.py
kalx/data/__init__.py
kalx/data/firebase_credentials.json
kalx/db/__init__.py
kalx/db/firebase_client.py
kalx/notifications/__init__.py
kalx/notifications/notification_manager.py
kalx/ui/__init__.py
kalx/ui/console.py
kalx/ui/cyberpunk.py
kalx/ui/menu.py
kalx/ui/notifications.py
kalx/ui/themes.py
kalx/utils/__init__.py
kalx/utils/config.py
kalx/utils/diagnostics.py
kalx/utils/encryption.py
kalx/utils/logger.py
kalx/utils/plugins.py
kalx/utils/scheduler.py
kalx/utils/setup.py
kalx-0.1.1.dist-info/METADATA
kalx-0.1.1.dist-info/WHEEL
kalx-0.1.1.dist-info/entry_points.txt
kalx-0.1.1.dist-info/top_level.txt
kalx-0.1.1.dist-info/RECORD
