Metadata-Version: 2.4
Name: kalx
Version: 0.1.1
Summary: A hacker-style console chat application
Author: kalX Developers
Requires-Python: >=3.8
Requires-Dist: firebase-admin>=5.0.0
Requires-Dist: rich>=10.0.0
Requires-Dist: prompt_toolkit>=3.0.0
Requires-Dist: cryptography>=3.4.0
Requires-Dist: python-dotenv>=0.19.0
Requires-Dist: requests>=2.25.0
Requires-Dist: pynput>=1.8.1
